HISTORY.rst
LICENSE.txt
MANIFEST.in
README.rst
setup.py
lib/nelmon/__init__.py
lib/nelmon/common.py
lib/nelmon/constants.py
lib/nelmon/globals.py
lib/nelmon.egg-info/PKG-INFO
lib/nelmon.egg-info/SOURCES.txt
lib/nelmon.egg-info/dependency_links.txt
lib/nelmon.egg-info/entry_points.txt
lib/nelmon.egg-info/requires.txt
lib/nelmon.egg-info/top_level.txt
lib/nelmon/args/__init__.py
lib/nelmon/args/base.py
lib/nelmon/args/notifier.py
lib/nelmon/args/plugin.py
lib/nelmon/cli/__init__.py
lib/nelmon/cli/check_admin_up_oper_down.py
lib/nelmon/cli/check_asa_connections.py
lib/nelmon/cli/check_environment.py
lib/nelmon/cli/check_uptime.py
lib/nelmon/cli/check_version.py
lib/nelmon/cli/notify_slack.py
lib/nelmon/snmp/__init__.py
lib/nelmon/snmp/args.py
lib/nelmon/snmp/handler.py
lib/nelmon/snmp/oids.py