Metadata-Version: 1.1
Name: nelmon
Version: 1.3.6
Summary: Monitoring Plugins for Nagios and compatible products
Home-page: https://networklore.com/nelmon/
Author: Patrick Ogenstad
Author-email: patrick@ogenstad.com
License: Apache
Platform: UNKNOWN
Classifier: Development Status :: 4 - Beta
Classifier: Intended Audience :: Developers
Classifier: Intended Audience :: System Administrators
